convexity_check/__init__.py
convexity_check/checker.py
convexity_check-0.0.4.dist-info/LICENSE
convexity_check-0.0.4.dist-info/METADATA
convexity_check-0.0.4.dist-info/WHEEL
convexity_check-0.0.4.dist-info/top_level.txt
convexity_check-0.0.4.dist-info/RECORD
